[
  {
    "name": "faction.black.name",
    "description": "faction.black.description",
    "image": "/assets/images/factions/black.png",
    "id": "black"
  },
  {
    "name": "faction.blue.name",
    "description": "faction.blue.description",
    "image": "/assets/images/factions/blue.png",
    "id": "blue"
  },
  {
    "name": "faction.green.name",
    "description": "faction.green.description",
    "image": "/assets/images/factions/green.png",
    "id": "green"
  },
  {
    "name": "faction.red.name",
    "description": "faction.red.description",
    "image": "/assets/images/factions/red.png",
    "id": "red"
  },
  {
    "name": "faction.white.name",
    "description": "faction.white.description",
    "image": "/assets/images/factions/white.png",
    "id": "white"
  },
  {
    "name": "faction.grey.name",
    "description": "faction.grey.description",
    "image": "/assets/images/factions/grey.png",
    "id": "grey"
  }
]
